django_comments/__init__.py
django_comments/abstracts.py
django_comments/admin.py
django_comments/compat.py
django_comments/feeds.py
django_comments/forms.py
django_comments/managers.py
django_comments/models.py
django_comments/moderation.py
django_comments/signals.py
django_comments/urls.py
django_comments/locale/ar/LC_MESSAGES/django.mo
django_comments/locale/ar/LC_MESSAGES/django.po
django_comments/locale/az/LC_MESSAGES/django.mo
django_comments/locale/az/LC_MESSAGES/django.po
django_comments/locale/be/LC_MESSAGES/django.mo
django_comments/locale/be/LC_MESSAGES/django.po
django_comments/locale/bg/LC_MESSAGES/django.mo
django_comments/locale/bg/LC_MESSAGES/django.po
django_comments/locale/bn/LC_MESSAGES/django.mo
django_comments/locale/bn/LC_MESSAGES/django.po
django_comments/locale/br/LC_MESSAGES/django.mo
django_comments/locale/br/LC_MESSAGES/django.po
django_comments/locale/bs/LC_MESSAGES/django.mo
django_comments/locale/bs/LC_MESSAGES/django.po
django_comments/locale/ca/LC_MESSAGES/django.mo
django_comments/locale/ca/LC_MESSAGES/django.po
django_comments/locale/cs/LC_MESSAGES/django.mo
django_comments/locale/cs/LC_MESSAGES/django.po
django_comments/locale/cy/LC_MESSAGES/django.mo
django_comments/locale/cy/LC_MESSAGES/django.po
django_comments/locale/da/LC_MESSAGES/django.mo
django_comments/locale/da/LC_MESSAGES/django.po
django_comments/locale/de/LC_MESSAGES/django.mo
django_comments/locale/de/LC_MESSAGES/django.po
django_comments/locale/el/LC_MESSAGES/django.mo
django_comments/locale/el/LC_MESSAGES/django.po
django_comments/locale/en/LC_MESSAGES/django.mo
django_comments/locale/en/LC_MESSAGES/django.po
django_comments/locale/en_GB/LC_MESSAGES/django.mo
django_comments/locale/en_GB/LC_MESSAGES/django.po
django_comments/locale/eo/LC_MESSAGES/django.mo
django_comments/locale/eo/LC_MESSAGES/django.po
django_comments/locale/es/LC_MESSAGES/django.mo
django_comments/locale/es/LC_MESSAGES/django.po
django_comments/locale/es_AR/LC_MESSAGES/django.mo
maykin_django_contrib_comments-1.8.0.dist-info/LICENSE.txt
maykin_django_contrib_comments-1.8.0.dist-info/METADATA
maykin_django_contrib_comments-1.8.0.dist-info/WHEEL
maykin_django_contrib_comments-1.8.0.dist-info/top_level.txt
maykin_django_contrib_comments-1.8.0.dist-info/RECORD
